conjuring/__init__.py
conjuring/__main__.py
conjuring/cli.py
conjuring/colors.py
conjuring/constants.py
conjuring/grimoire.py
conjuring/spells/__init__.py
conjuring/spells/aws.py
conjuring/spells/direnv.py
conjuring/spells/docker.py
conjuring/spells/duplicity.py
conjuring/spells/fork.py
conjuring/spells/generic.py
conjuring/spells/git.py
conjuring/spells/jrnl.py
conjuring/spells/k8s.py
conjuring/spells/media.py
conjuring/spells/mkdocs.py
conjuring/spells/mr.py
conjuring/spells/onedrive.py
conjuring/spells/paperless.py
conjuring/spells/pre_commit.py
conjuring/spells/py.py
conjuring/spells/shell.py
conjuring/visibility.py
conjuring-0.7.0.dist-info/METADATA
conjuring-0.7.0.dist-info/WHEEL
conjuring-0.7.0.dist-info/entry_points.txt
conjuring-0.7.0.dist-info/RECORD
