Metadata-Version: 2.1
Name: conjuring
Version: 0.7.0
Summary: 🐍🤖 Reusable global Invoke tasks that can be merged with local project tasks
Home-page: https://github.com/andreoliwa/conjuring
License: MIT
Keywords: invoke,tasks,automation,cli,python
Author: W. Augusto Andreoli
Author-email: andreoliwa@gmail.com
Requires-Python: >=3.9,<4.0
Classifier: Development Status :: 4 - Beta
Classifier: Environment :: Console
Classifier: Intended Audience :: Developers
Classifier: License :: OSI Approved :: MIT License
Classifier: Operating System :: MacOS
Classifier: Operating System :: Microsoft :: Windows
Classifier: Operating System :: POSIX :: Linux
Classifier: Programming Language :: Python :: 3
Classifier: Programming Language :: Python :: 3.9
Classifier: Programming Language :: Python :: 3.10
Classifier: Programming Language :: Python :: 3.11
Classifier: Topic :: Software Development
Requires-Dist: invoke
Requires-Dist: iterfzf
Requires-Dist: requests
Requires-Dist: ruamel-yaml
Requires-Dist: typer
Project-URL: Documentation, https://andreoliwa.github.io/conjuring/
Project-URL: Repository, https://github.com/andreoliwa/conjuring
